mat3ra/__init__.py
mat3ra/prode/__init__.py
mat3ra_prode-2026.1.23.post0.dist-info/licenses/LICENSE.md
mat3ra_prode-2026.1.23.post0.dist-info/METADATA
mat3ra_prode-2026.1.23.post0.dist-info/WHEEL
mat3ra_prode-2026.1.23.post0.dist-info/top_level.txt
mat3ra_prode-2026.1.23.post0.dist-info/RECORD
