Metadata-Version: 2.4
Name: mat3ra-prode
Version: 2026.1.23.post0
Summary: PROperty DEfinitions
Author-email: "Exabyte Inc." <info@mat3ra.com>
License: Apache-2.0
Classifier: Programming Language :: Python :: 3
Classifier: Programming Language :: Python :: 3.10
Classifier: Programming Language :: Python :: 3.11
Classifier: Programming Language :: Python :: 3.12
Classifier: Programming Language :: Python :: 3.13
Classifier: License :: OSI Approved :: Apache Software License
Classifier: Operating System :: OS Independent
Requires-Python: >=3.10
License-File: LICENSE.md
Requires-Dist: numpy
Provides-Extra: dev
Requires-Dist: pre-commit; extra == "dev"
Requires-Dist: black; extra == "dev"
Requires-Dist: ruff; extra == "dev"
Requires-Dist: isort; extra == "dev"
Provides-Extra: tests
Requires-Dist: coverage[toml]>=5.3; extra == "tests"
Requires-Dist: pytest; extra == "tests"
Requires-Dist: pytest-cov; extra == "tests"
Provides-Extra: all
Requires-Dist: mat3ra-prode[dev]; extra == "all"
Requires-Dist: mat3ra-prode[tests]; extra == "all"
Dynamic: license-file
